skift/__init__.py
skift/_version.py
skift/core.py
skift/util.py
tests/__init__.py
tests/test_common.py
tests/test_pickle.py
skift-0.0.23.dist-info/LICENSE
skift-0.0.23.dist-info/METADATA
skift-0.0.23.dist-info/WHEEL
skift-0.0.23.dist-info/top_level.txt
skift-0.0.23.dist-info/RECORD
